smrtnet/__init__.py
smrtnet/explain.py
smrtnet/infer.py
smrtnet/inference.py
smrtnet/loader.py
smrtnet/loop.py
smrtnet/model.py
smrtnet/utils.py
smrtnet/visual.py
smrtnet/visual_RNA.py
smrtnet/LM_Mol/__init__.py
smrtnet/LM_Mol/attention_layer.py
smrtnet/LM_Mol/bert_vocab.txt
smrtnet/LM_Mol/rotary.py
smrtnet/LM_Mol/rotate_builder.py
smrtnet/LM_Mol/tokenizer.py
smrtnet/LM_RNA/__init__.py
smrtnet/LM_RNA/activations.py
smrtnet/LM_RNA/bert.py
smrtnet/LM_RNA/doc.py
smrtnet/LM_RNA/modeling_utils.py
smrtnet/LM_RNA/transformers_output.py
smrtnet/data/SMRTnet-data-demo.txt
smrtnet/data/SMRTnet_data.txt
smrtnet/data/__init__.py
smrtnet/fast_transformers/__init__.py
smrtnet/fast_transformers/masking.py
smrtnet/fast_transformers/transformers.py
smrtnet/fast_transformers/utils.py
smrtnet/fast_transformers/weight_mapper.py
smrtnet/fast_transformers/aggregate/__init__.py
smrtnet/fast_transformers/attention/__init__.py
smrtnet/fast_transformers/attention/attention_layer.py
smrtnet/fast_transformers/attention/causal_linear_attention.py
smrtnet/fast_transformers/attention/clustered_attention.py
smrtnet/fast_transformers/attention/conditional_full_attention.py
smrtnet/fast_transformers/attention/exact_topk_attention.py
smrtnet/fast_transformers/attention/full_attention.py
smrtnet/fast_transformers/attention/improved_clustered_attention.py
smrtnet/fast_transformers/attention/improved_clustered_causal_attention.py
smrtnet/fast_transformers/attention/linear_attention.py
smrtnet/fast_transformers/attention/local_attention.py
smrtnet/fast_transformers/attention/reformer_attention.py
smrtnet/fast_transformers/attention_registry/__init__.py
smrtnet/fast_transformers/attention_registry/registry.py
smrtnet/fast_transformers/attention_registry/spec.py
smrtnet/fast_transformers/builders/__init__.py
smrtnet/fast_transformers/builders/attention_builders.py
smrtnet/fast_transformers/builders/base.py
smrtnet/fast_transformers/builders/transformer_builders.py
smrtnet_latest-0.25.dist-info/LICENSE
smrtnet_latest-0.25.dist-info/METADATA
smrtnet_latest-0.25.dist-info/WHEEL
smrtnet_latest-0.25.dist-info/top_level.txt
smrtnet_latest-0.25.dist-info/RECORD
