Metadata-Version: 2.1
Name: smrtnet_latest
Version: 0.25
Summary: A python lib for predicting small molecule-RNA interactions (SRIs)
Home-page: https://github.com/Yuhan-Fei/SMRTnet
Author: yuhan_Fei & jiasheng_Zhang
Author-email: yuhan_fei@outlook.com
License: MIT
Requires-Python: ==3.8.10
License-File: LICENSE
Requires-Dist: babel
Requires-Dist: charset-normalizer==3.3.2
Requires-Dist: dgllife
Requires-Dist: matplotlib
Requires-Dist: networkx
Requires-Dist: huggingface-hub
Requires-Dist: notebook
Requires-Dist: numpy
Requires-Dist: pandas
Requires-Dist: prefetch-generator
Requires-Dist: prettytable
Requires-Dist: pytorch-lightning
Requires-Dist: rdkit==2022.3.5
Requires-Dist: scikit-learn
Requires-Dist: scipy
Requires-Dist: seaborn
Requires-Dist: tensorboard
Requires-Dist: tensorboardX
Requires-Dist: tqdm
Requires-Dist: transformers==4.28.1
Requires-Dist: xsmiles
